<?xml version="1.0" encoding="utf-8" ?>
<dwsync>
<file name="battlemusic.mp3" server="W:/" local="131080023563268313" remote="131080023560000000" Dst="1" />
<file name="battlemusic.ogg" server="W:/" local="131080025056025965" remote="131080025050000000" Dst="1" />
<file name="battlemusic.mp3" server="samcalamos.netne.net/public_html/" local="131083831677033559" remote="131083353000000000" Dst="1" />
<file name="battlemusic.ogg" server="samcalamos.netne.net/public_html/" local="131083831677248766" remote="131083353000000000" Dst="1" />
<file name="countdown.ogg" server="samcalamos.netne.net/public_html/" local="131084777742244947" remote="131084278800000000" Dst="1" />
<file name="gotCode.ogg" server="samcalamos.netne.net/public_html/" local="131083881956210705" remote="131083384800000000" Dst="1" />
<file name="story.ogg" server="samcalamos.netne.net/public_html/" local="131083897330922757" remote="131083395600000000" Dst="1" />
<file name="Countdown - Clock Only.mp3" server="W:/" local="131084356490464499" remote="131084356490000000" Dst="1" />
<file name="countdown.ogg" server="W:/" local="131084357001241827" remote="131084357000000000" Dst="1" />
<file name="gotCode.ogg" server="W:/" local="131084353893893861" remote="131084353890000000" Dst="1" />
<file name="story.ogg" server="W:/" local="131084353894083967" remote="131084353890000000" Dst="1" />
<file name="Countdown - Clock Only.mp3" server="samcalamos.netne.net/public_html/" local="131084777742174832" remote="131084278800000000" Dst="1" />
</dwsync>